quote/__init__.py
quote/cli.py
quote/py.typed
quote/quote.py
quote/spinner.py
quote-3.0.dist-info/LICENSE
quote-3.0.dist-info/METADATA
quote-3.0.dist-info/WHEEL
quote-3.0.dist-info/entry_points.txt
quote-3.0.dist-info/top_level.txt
quote-3.0.dist-info/RECORD
