Metadata-Version: 2.1
Name: quote
Version: 3.0
Summary: A wrapper for the Goodreads Quote API
Home-page: https://github.com/maxhumber/quote
Author: Max Humber
Author-email: max.humber@gmail.com
Keywords: quote,quotes,goodreads,wrapper,api
Classifier: Development Status :: 5 - Production/Stable
Classifier: Natural Language :: English
Classifier: Programming Language :: Python :: 3
Classifier: License :: OSI Approved :: MIT License
Requires-Python: >=3.7
License-File: LICENSE
Requires-Dist: gazpacho>=1.0
